ProcessCheckerLib/ProcessCheckerLib.py
ProcessCheckerLib/__init__.py
ProcessCheckerLib-0.0.4.dist-info/METADATA
ProcessCheckerLib-0.0.4.dist-info/WHEEL
ProcessCheckerLib-0.0.4.dist-info/top_level.txt
ProcessCheckerLib-0.0.4.dist-info/RECORD
