Metadata-Version: 2.1
Name: ProcessCheckerLib
Version: 0.0.4
Summary: This is lib for work with scripts exceptions.
Home-page: 
Author: Brambleaka
Author-email: sambuka11jail@outlook.com
Classifier: Programming Language :: Python :: 3.12
Classifier: License :: OSI Approved :: MIT License
Classifier: Operating System :: OS Independent
Requires-Python: >=3.11
Requires-Dist: requests
Requires-Dist: psutil
Requires-Dist: flask
Requires-Dist: schedule
Requires-Dist: logging
Requires-Dist: werkzeug
